restless_client/__init__.py
restless_client/client.py
restless_client/collections.py
restless_client/connection.py
restless_client/filter.py
restless_client/inspect.py
restless_client/marshal.py
restless_client/method.py
restless_client/models.py
restless_client/property.py
restless_client/types.py
restless_client/utils.py
restless_client/ext/auth.py
flask_restless_client-0.4.14.dist-info/AUTHORS
flask_restless_client-0.4.14.dist-info/LICENSE
flask_restless_client-0.4.14.dist-info/METADATA
flask_restless_client-0.4.14.dist-info/WHEEL
flask_restless_client-0.4.14.dist-info/pbr.json
flask_restless_client-0.4.14.dist-info/top_level.txt
flask_restless_client-0.4.14.dist-info/RECORD
