Metadata-Version: 2.1
Name: flask-restless-client
Version: 0.4.14
Summary: CRUD/RPC client over flask-restless
Home-page: https://github.com/maarten-dp/flask-restless-client
Author: Maarten De Paepe
Author-email: "maarten.de.paepe@gmail.com"
Classifier: Development Status :: 4 - Beta
Classifier: Operating System :: MacOS :: MacOS X
Classifier: Operating System :: Microsoft :: Windows
Classifier: Operating System :: POSIX
Classifier: License :: OSI Approved :: MIT License
Classifier: Programming Language :: Python
Classifier: Programming Language :: Python :: 3.7
License-File: LICENSE
License-File: AUTHORS
Requires-Dist: cereal-lazer
Requires-Dist: crayons
Requires-Dist: dateutils
Requires-Dist: ordered-set ==3.1
Requires-Dist: packaging
Requires-Dist: pbr
Requires-Dist: prettytable
Requires-Dist: requests
